Workbook

Sheet Resumen
A1: ACTIVIDAD APLICATIVA N° 07
A2: Empresa Mi Alto Perú - Planilla de Remuneraciones - Régimen Construcción Civil
A3: Período: 06/04 al 11/04 (6 días) | Curso: Contabilidad Sectorial | Dra. Luz R. Lapa Salinas | Ciclo VI – Noche
A5: CUADRO COMPARATIVO
A7: Concepto | B7: Cruz Alonso (Operario) | C7: Salas Diego (Oficial) | D7: Pérez Gino (Peón) | E7: Totales
A8: Jornal semanal | B8: ='T1 - Cruz Alonso'!D11 -> 535.8 | C8: ='T2 - Salas Diego'!D11 -> 418.5 | D8: ='T3 - Pérez Gino'!D11 -> 376.8 | E8: =SUM(B8:D8) -> 1331.1
A9: DSO | B9: ='T1 - Cruz Alonso'!D15 -> 89.3 | C9: ='T2 - Salas Diego'!D15 -> 69.75 | D9: ='T3 - Pérez Gino'!D15 -> 62.8 | E9: =SUM(B9:D9) -> 221.85
A10: BUC | B10: ='T1 - Cruz Alonso'!D19 -> 171.456 | C10: ='T2 - Salas Diego'!D19 -> 125.55 | D10: ='T3 - Pérez Gino'!D19 -> 113.04 | E10: =SUM(B10:D10) -> 410.046
A11: Movilidad | B11: ='T1 - Cruz Alonso'!D23 -> 51.6 | C11: ='T2 - Salas Diego'!D23 -> 51.6 | D11: ='T3 - Pérez Gino'!D23 -> 51.6 | E11: =SUM(B11:D11) -> 154.8
A12: Bonif. altitud | B12: 0 | C12: ='T2 - Salas Diego'!D27 -> 15 | D12: ='T3 - Pérez Gino'!D27 -> 15 | E12: =SUM(B12:D12) -> 30
A13: Bonif. altura | B13: 0 | C13: ='T2 - Salas Diego'!F31 -> 33.48 | D13: 0 | E13: =SUM(B13:D13) -> 33.48
A14: Indemnización CTS | B14: ='T1 - Cruz Alonso'!D27 -> 80.37 | C14: ='T2 - Salas Diego'!D35 -> 62.775 | D14: ='T3 - Pérez Gino'!D31 -> 56.52 | E14: =SUM(B14:D14) -> 199.665
A15: Vacaciones | B15: ='T1 - Cruz Alonso'!D31 -> 53.58 | C15: ='T2 - Salas Diego'!D39 -> 41.85 | D15: ='T3 - Pérez Gino'!D35 -> 37.68 | E15: =SUM(B15:D15) -> 133.11
A16: Gratificaciones | B16: ='T1 - Cruz Alonso'!E36 -> 119.06667 | C16: ='T2 - Salas Diego'!E44 -> 93 | D16: ='T3 - Pérez Gino'!E40 -> 83.733333 | E16: =SUM(B16:D16) -> 295.8
A17: Bonificación extraord. | B17: ='T1 - Cruz Alonso'!D40 -> 10.716 | C17: ='T2 - Salas Diego'!D48 -> 8.37 | D17: ='T3 - Pérez Gino'!D44 -> 7.536 | E17: =SUM(B17:D17) -> 26.622
A18: Asignación escolar | B18: ='T1 - Cruz Alonso'!F45 -> 104.18333 | C18: ='T2 - Salas Diego'!F53 -> 40.6875 | D18: ='T3 - Pérez Gino'!F48 -> 0 | E18: =SUM(B18:D18) -> 144.87083
A19: Horas extra | B19: ='T1 - Cruz Alonso'!E54 -> 174.135 | C19: ='T2 - Salas Diego'!E62 -> 160.425 | D19: ='T3 - Pérez Gino'!E57 -> 25.12 | E19: =SUM(B19:D19) -> 359.68
A20: Indemnización HE | B20: ='T1 - Cruz Alonso'!D58 -> 100.44 | C20: ='T2 - Salas Diego'!D66 -> 87.2 | D20: ='T3 - Pérez Gino'!D61 -> 15.7 | E20: =SUM(B20:D20) -> 203.34
A22: TOTAL INGRESOS BRUTOS | B22: ='T1 - Cruz Alonso'!D61 -> 1490.647 | C22: ='T2 - Salas Diego'!D69 -> 1180.2875 | D22: ='T3 - Pérez Gino'!D64 -> 845.52933 | E22: =SUM(B22:D22) -> 3516.4638
A23: Base afecta | B23: ='T1 - Cruz Alonso'!D65 -> 1128.4543 | C23: ='T2 - Salas Diego'!D73 -> 905.2425 | D23: ='T3 - Pérez Gino'!D68 -> 630.44 | E23: =SUM(B23:D23) -> 2664.1368
A24: Total descuentos (ONP+CONAFOVICER) | B24: ='T1 - Cruz Alonso'!C72 -> 169.26815 | C24: ='T2 - Salas Diego'!C80 -> 135.78638 | D24: ='T3 - Pérez Gino'!C75 -> 94.566 | E24: =SUM(B24:D24) -> 399.62053
A25: SALARIO NETO A PAGAR | B25: ='T1 - Cruz Alonso'!D74 -> 1321.3789 | C25: ='T2 - Salas Diego'!D82 -> 1044.5011 | D25: ='T3 - Pérez Gino'!D77 -> 750.96333 | E25: =SUM(B25:D25) -> 3116.8433
A26: Total aportes empleador (ESSALUD+SENCICO) | B26: ='T1 - Cruz Alonso'!C80 -> 103.8178 | C26: ='T2 - Salas Diego'!C88 -> 83.28231 | D26: ='T3 - Pérez Gino'!C83 -> 58.00048 | E26: =SUM(B26:D26) -> 245.10059
A27: COSTO TOTAL EMPRESA | B27: ='T1 - Cruz Alonso'!D83 -> 1594.4648 | C27: ='T2 - Salas Diego'!D91 -> 1263.5698 | D27: ='T3 - Pérez Gino'!D86 -> 903.52981 | E27: =SUM(B27:D27) -> 3761.5644
A30: Nota metodológica:
A31: • Régimen: Construcción Civil (D. Leg. 727 y convenios colectivos vigentes).
A32: • Jornales básicos: Operario S/ 89.30 | Oficial S/ 69.75 | Peón S/ 62.80.
A33: • BUC: 32% operario / 30% oficial / 30% peón sobre jornal básico × días trabajados.
A34: • CTS = 15% del jornal semanal | Vacaciones = 10% del jornal semanal.
A35: • Gratificaciones = 40 jornales prorrateados (jornal × 40 / 7 / 30 × 7 días).
A36: • Bonificación extraordinaria = 9% de la gratificación (Ley 30334).
A37: • Asignación escolar = jornal × 30 / 360 × 7 × N° hijos en edad escolar.
A38: • HE: 1ras 2 diarias al 60% de recargo, desde la 3ra al 100%.
A39: • Bonif. altitud: S/ 2.50/día (> 3,000 msnm). Bonif. altura: 8% del jornal por cada 4 pisos (desde el 4° piso).
A40: • Base afecta: jornal semanal + DSO + BUC + vacaciones + asignación familiar + HE + altitud + altura.
A41: • Descuentos: ONP 13% | CONAFOVICER 2%. Aportes empleador: ESSALUD 9% | SENCICO 0.2%.

Sheet T1 - Cruz Alonso
A1: EMPRESA MI ALTO PERÚ - CONSTRUCTORA
A2: Planilla de Remuneraciones - Régimen Construcción Civil
A4: Trabajador: | B4: Cruz Alonso
A5: Categoría: | B5: Operario
A6: Período: | B6: 06/04 al 11/04 (6 días)
A7: Régimen pensionario: | B7: ONP
A9: 1. JORNADA SEMANAL
A10: Jornal básico × días trabajados
A11: Jornal básico (S/) | B11: 89.3 | C11: 6 días | D11: =B11*6 -> 535.8
A13: 2. DESCANSO SEMANAL OBLIGATORIO
A14: Equivale a 1 jornal diario
B15: =B11 -> 89.3 | C15: 1 día | D15: =B15 -> 89.3
A17: 3. BONIFICACIÓN UNIFICADA DE CONSTRUCCIÓN (BUC)
A18: Operario: 32% del jornal diario por día trabajado
B19: =D11 -> 535.8 | C19: 0.32 | D19: =B19*C19 -> 171.456
A21: 4. MOVILIDAD
A22: S/ 8.60 por día trabajado
B23: 8.6 | C23: 6 días | D23: =B23*6 -> 51.6
A25: 7. INDEMNIZACIÓN CTS
A26: 15% del jornal semanal | F26: ESTO NO ESTA EN LA TEORIA, PERO APARECE EN TODOS
B27: =D11 -> 535.8 | C27: 0.15 | D27: =B27*C27 -> 80.37
A29: 8. VACACIONES
A30: 10% del jornal semanal
B31: =D11 -> 535.8 | C31: 0.1 | D31: =B31*C31 -> 53.58
A33: 9. GRATIFICACIONES
A34: 40 jornales anuales prorrateados (jornal × 40 / 7 / 30)
A35: Cálculo base (por día): | B35: =B11 -> 89.3 | C35: 40 | D35: =B35*C35 -> 3572 | E35: 7 | F35: 30 | G35: =D35/E35/F35 -> 17.009524
A36: Aplicado a la semana (× 7 días): | C36: =G35 -> 17.009524 | D36: 7 | E36: =C36*D36 -> 119.06667
A38: 10. BONIFICACIÓN EXTRAORDINARIA
A39: 9% de la gratificación (Ley 30334) | F39: ESTO NO ESTA EN LA TEORIA, PERO APARECE EN TODOS
B40: =E36 -> 119.06667 | C40: 0.09 | D40: =B40*C40 -> 10.716
A42: 11. ASIGNACIÓN ESCOLAR (Escolaridad)
A43: 30 jornales × jornal diario / 360 días × 7 días × N° hijos en edad escolar
B44: =B11 -> 89.3 | C44: 30 | D44: 360 | E44: 7 | F44: =B44*C44/D44*E44 -> 52.091667
D45: Por hijo | E45: 2 | F45: =F44*E45 -> 104.18333
A47: 12. HORAS EXTRA
A48: En función al jornal diario (3d × 3h)
A49: Valor hora ordinaria: | C49: =B11 -> 89.3 | D49: 8 | E49: =C49/D49 -> 11.1625
C51: HE | D51: Valor hora | E51: Total
A52: 60% (1ras 2 HE diarias) | B52: 0.6 | C52: 6 | D52: =E49 -> 11.1625 | E52: =D52*(B52+1)*C52 -> 107.16
A53: 100% (3ra HE en adelante) | B53: 1 | C53: 3 | D53: =E49 -> 11.1625 | E53: =D53*(B53+1)*C53 -> 66.975
A54: Total HE | C54: =SUM(C52:C53) -> 9 | E54: =SUM(E52:E53) -> 174.135
A56: 13. INDEMNIZACIÓN HORAS EXTRA
A57: Valor de una hora ordinaria × N° de HE
B58: =ROUND(E49,2) -> 11.16 | C58: =C54 -> 9 | D58: =B58*C58 -> 100.44
A61: TOTAL INGRESOS BRUTOS | D61: =D11+D15+D19+D23+D27+D31+E36+D40+F45+E54+D58 -> 1490.647
A63: BASE AFECTA (para aportes y descuentos)
A64: Incluye: Jornal semanal + DSO + BUC + Vacaciones + Asig. familiar + HE + Altitud + Altura
D65: =D11+D15+D19+D31+F45+E54 -> 1128.4543
A66: No se considera: Indemnizaciones, Gratificaciones, Bonif. extraordinaria, Movilidad
A69: DESCUENTOS AL TRABAJADOR
A70: ONP | B70: 0.13 | C70: =$D$65*B70 -> 146.69906
A71: CONAFOVICER | B71: 0.02 | C71: =$D$65*B71 -> 22.569087
A72: Total descuentos | C72: =SUM(C70:C71) -> 169.26815
A74: TOTAL SALARIO NETO A PAGAR | D74: =D61-C72 -> 1321.3789
A77: APORTES DEL EMPLEADOR
A78: ESSALUD | B78: 0.09 | C78: =$D$65*B78 -> 101.56089
A79: SENCICO | B79: 0.002 | C79: =$D$65*B79 -> 2.2569087
A80: Total aportes empleador | C80: =SUM(C78:C79) -> 103.8178
A83: COSTO TOTAL PARA LA EMPRESA | D83: =D61+C80 -> 1594.4648
A86: Notas:
A87: • 9 HE totales: 6 al 60% (1ras 2 de cada día × 3 días) + 3 al 100% (3era HE de cada día × 3 días).
A88: • Asignación escolar por 2 hijos en edad escolar.
G90: =SUM(G92:G262) -> 4510.3084 | H90: =SUM(H92:H262) -> 4510.3084 | I90: =G90-H90 -> 0
E91: CTA | F91: Descrip. Cta | G91: DEBE | H91: HABER
C92: Planilla de remuneraciones | E92: 6211 | F92: Jornal básico | G92: =D11 -> 535.8
E93: 6214 | F93: Gratificaciones | G93: =E36 -> 119.06667
E94: 6215 | F94: Vacaciones | G94: =D31 -> 53.58
E95: 6221 | F95: Descanso S. Obli. | G95: =D15 -> 89.3
E96: 6222 | F96: BUC | G96: =D19 -> 171.456
E97: 6223 | F97: Movilidad | G97: =D23 -> 51.6
E98: 6224 | F98: Boni. Extraor. | G98: =D40 -> 10.716
E99: 6225 | F99: Escolaridad | G99: =F45 -> 104.18333
E100: 6226 | F100: Horas Extra | G100: =E54 -> 174.135
E101: 6231 | F101: Indemnización CTS | G101: =D27 -> 80.37
E102: 6232 | F102: Indemnización HE | G102: =D58 -> 100.44
E103: 6271 | F103: EsSalud | G103: =C78 -> 101.56089
E104: 6278 | F104: CENCICO | G104: =C79 -> 2.2569087
E105: 4031 | F105: EsSalud | H105: =G103 -> 101.56089
E106: 4032 | F106: ONP | H106: =C70 -> 146.69906
E107: 4034 | F107: CENCICO | H107: =G104 -> 2.2569087
E108: 40391 | F108: CONAFOVICER | H108: =C71 -> 22.569087
E109: 4111 | F109: Neto | H109: =D74 -> 1321.3789
C110: Pago de planilla | E110: 4111 | F110: Neto | G110: =H109 -> 1321.3789
E111: 1041 | F111: Neto | H111: =G110 -> 1321.3789
C112: Destino del gasto | E112: 91 | G112: =SUM(G92:G104) -> 1594.4648
E113: 79 | H113: =G112 -> 1594.4648

Sheet T2 - Salas Diego
A1: EMPRESA MI ALTO PERÚ - CONSTRUCTORA
A2: Planilla de Remuneraciones - Régimen Construcción Civil
A4: Trabajador: | B4: Salas Diego
A5: Categoría: | B5: Oficial
A6: Período: | B6: 06/04 al 11/04 (6 días)
A7: Régimen pensionario: | B7: ONP
A9: 1. JORNADA SEMANAL
A10: Jornal básico × días trabajados
A11: Jornal básico (S/) | B11: 69.75 | C11: 6 días | D11: =B11*6 -> 418.5
A13: 2. DESCANSO SEMANAL OBLIGATORIO
A14: Equivale a 1 jornal diario
B15: =B11 -> 69.75 | C15: 1 día | D15: =B15 -> 69.75
A17: 3. BONIFICACIÓN UNIFICADA DE CONSTRUCCIÓN (BUC)
A18: Oficial: 30% del jornal diario por día trabajado
B19: =D11 -> 418.5 | C19: 0.3 | D19: =B19*C19 -> 125.55
A21: 4. MOVILIDAD
A22: S/ 8.60 por día trabajado
B23: 8.6 | C23: 6 días | D23: =B23*6 -> 51.6
A25: 5. BONIFICACIÓN POR ALTITUD
A26: S/ 2.50 por día trabajado (obra > 3,000 msnm)
B27: 2.5 | C27: 6 días | D27: =B27*6 -> 15 | E27: si se multiplica por dias
A29: 6. BONIFICACIÓN POR ALTURA
A30: 8% sobre jornal básico por cada 4 pisos (a partir del 4°). Obra de 7 pisos → 8% | F30: La profe dice que no se multiplica por dias laborados | J30: PREGUNTAR SI, CUANDO HAY MAS DE 8 PISOS, ME DEBERAN PAGAR 16% O SOLO SE MANTIENE EL 8%
B31: =B11 -> 69.75 | C31: 0.08 | D31: =B31*C31 -> 5.58 | E31: 6 días | F31: =D31*6 -> 33.48
A33: 7. INDEMNIZACIÓN CTS
A34: 15% del jornal semanal
B35: =D11 -> 418.5 | C35: 0.15 | D35: =B35*C35 -> 62.775
A37: 8. VACACIONES
A38: 10% del jornal semanal
B39: =D11 -> 418.5 | C39: 0.1 | D39: =B39*C39 -> 41.85
A41: 9. GRATIFICACIONES
A42: 40 jornales anuales prorrateados (jornal × 40 / 7 / 30)
A43: Cálculo base (por día): | B43: =B11 -> 69.75 | C43: 40 | D43: =B43*C43 -> 2790 | E43: 7 | F43: 30 | G43: =D43/E43/F43 -> 13.285714
A44: Aplicado a la semana (× 7 días): | C44: =G43 -> 13.285714 | D44: 7 | E44: =C44*D44 -> 93
A46: 10. BONIFICACIÓN EXTRAORDINARIA
A47: 9% de la gratificación (Ley 30334)
B48: =E44 -> 93 | C48: 0.09 | D48: =B48*C48 -> 8.37
A50: 11. ASIGNACIÓN ESCOLAR
A51: 30 jornales × jornal diario / 360 días × 7 días × N° hijos en edad escolar
B52: =B11 -> 69.75 | C52: 30 | D52: 360 | E52: 7 | F52: =B52*C52/D52*E52 -> 40.6875
D53: Por hijo | E53: 1 | F53: =F52*E53 -> 40.6875
A55: 12. HORAS EXTRA
A56: En función al jornal diario (2d × 5h)
A57: Valor hora ordinaria: | C57: =B11 -> 69.75 | D57: 8 | E57: =C57/D57 -> 8.71875
C59: HE | D59: Valor hora | E59: Total
A60: 60% (1ras 2 HE diarias) | B60: 0.6 | C60: 4 | D60: =E57 -> 8.71875 | E60: =D60*(B60+1)*C60 -> 55.8
A61: 100% (3ra HE en adelante) | B61: 1 | C61: 6 | D61: =E57 -> 8.71875 | E61: =D61*(B61+1)*C61 -> 104.625
A62: Total HE | C62: =SUM(C60:C61) -> 10 | E62: =SUM(E60:E61) -> 160.425
A64: 13. INDEMNIZACIÓN HORAS EXTRA
A65: Valor de una hora ordinaria × N° de HE
B66: =ROUND(E57,2) -> 8.72 | C66: =C62 -> 10 | D66: =B66*C66 -> 87.2
A69: TOTAL INGRESOS BRUTOS | D69: =D11+D15+D19+D23+D27+D31+D35+D39+E44+D48+F53+E62+D66 -> 1180.2875
A71: BASE AFECTA (para aportes y descuentos)
A72: Incluye: Jornal semanal + DSO + BUC + Vacaciones + Asig. familiar + HE + Altitud + Altura
D73: =D11+D15+D19+D39+F53+E62+D27+F31 -> 905.2425
A74: No se considera: Indemnizaciones, Gratificaciones, Bonif. extraordinaria, Movilidad
A77: DESCUENTOS AL TRABAJADOR
A78: ONP | B78: 0.13 | C78: =$D$73*B78 -> 117.68153
A79: CONAFOVICER | B79: 0.02 | C79: =$D$73*B79 -> 18.10485
A80: Total descuentos | C80: =SUM(C78:C79) -> 135.78638
A82: TOTAL SALARIO NETO A PAGAR | D82: =D69-C80 -> 1044.5011
A85: APORTES DEL EMPLEADOR
A86: ESSALUD | B86: 0.09 | C86: =$D$73*B86 -> 81.471825
A87: SENCICO | B87: 0.002 | C87: =$D$73*B87 -> 1.810485
A88: Total aportes empleador | C88: =SUM(C86:C87) -> 83.28231
A91: COSTO TOTAL PARA LA EMPRESA | D91: =D69+C88 -> 1263.5698
A94: Notas:
A95: • 10 HE totales: 4 al 60% (1ras 2 de cada día × 2 días) + 6 al 100% (3era a 5ta HE × 2 días).
A96: • Bonif. altitud: obra a 4,500 msnm (> 3,000 msnm) → S/ 2.50 × 6 días.
A97: • Bonif. altura: obra de 7 pisos → 1 bloque de 4 pisos a partir del 4° → 8% sobre jornal × 6 días.
A98: • Asignación escolar: solo se considera el hijo en edad escolar. El bebé de 3 meses no genera asignación escolar (régimen de construcción civil reconoce solo hijos cursando educación inicial / primaria / secundaria, hasta 18 años).

Sheet T3 - Pérez Gino
A1: EMPRESA MI ALTO PERÚ - CONSTRUCTORA
A2: Planilla de Remuneraciones - Régimen Construcción Civil
A4: Trabajador: | B4: Pérez Gino
A5: Categoría: | B5: Peón
A6: Período: | B6: 06/04 al 11/04 (6 días)
A7: Régimen pensionario: | B7: ONP
A9: 1. JORNADA SEMANAL
A10: Jornal básico × días trabajados
A11: Jornal básico (S/) | B11: 62.8 | C11: 6 días | D11: =B11*6 -> 376.8
A13: 2. DESCANSO SEMANAL OBLIGATORIO
A14: Equivale a 1 jornal diario
B15: =B11 -> 62.8 | C15: 1 día | D15: =B15 -> 62.8
A17: 3. BONIFICACIÓN UNIFICADA DE CONSTRUCCIÓN (BUC)
A18: Peón: 30% del jornal diario por día trabajado
B19: =D11 -> 376.8 | C19: 0.3 | D19: =B19*C19 -> 113.04
A21: 4. MOVILIDAD
A22: S/ 8.60 por día trabajado
B23: 8.6 | C23: 6 días | D23: =B23*6 -> 51.6
A25: 5. BONIFICACIÓN POR ALTITUD
A26: S/ 2.50 por día trabajado (obra > 3,000 msnm)
B27: 2.5 | C27: 6 días | D27: =B27*6 -> 15
A29: 7. INDEMNIZACIÓN CTS
A30: 15% del jornal semanal
B31: =D11 -> 376.8 | C31: 0.15 | D31: =B31*C31 -> 56.52
A33: 8. VACACIONES
A34: 10% del jornal semanal
B35: =D11 -> 376.8 | C35: 0.1 | D35: =B35*C35 -> 37.68
A37: 9. GRATIFICACIONES
A38: 40 jornales anuales prorrateados (jornal × 40 / 7 / 30)
A39: Cálculo base (por día): | B39: =B11 -> 62.8 | C39: 40 | D39: =B39*C39 -> 2512 | E39: 7 | F39: 30 | G39: =D39/E39/F39 -> 11.961905
A40: Aplicado a la semana (× 7 días): | C40: =G39 -> 11.961905 | D40: 7 | E40: =C40*D40 -> 83.733333
A42: 10. BONIFICACIÓN EXTRAORDINARIA
A43: 9% de la gratificación (Ley 30334)
B44: =E40 -> 83.733333 | C44: 0.09 | D44: =B44*C44 -> 7.536
A46: 11. ASIGNACIÓN ESCOLAR
A47: No aplica (sin hijos en edad escolar)
F48: 0
A50: 12. HORAS EXTRA
A51: En función al jornal diario (2d × 1h)
A52: Valor hora ordinaria: | C52: =B11 -> 62.8 | D52: 8 | E52: =C52/D52 -> 7.85
C54: HE | D54: Valor hora | E54: Total
A55: 60% (1ras 2 HE diarias) | B55: 0.6 | C55: 2 | D55: =E52 -> 7.85 | E55: =D55*(B55+1)*C55 -> 25.12
A56: 100% (3ra HE en adelante) | B56: 1 | C56: 0 | D56: =E52 -> 7.85 | E56: =D56*(B56+1)*C56 -> 0
A57: Total HE | C57: =SUM(C55:C56) -> 2 | E57: =SUM(E55:E56) -> 25.12
A59: 13. INDEMNIZACIÓN HORAS EXTRA
A60: Valor de una hora ordinaria × N° de HE
B61: =ROUND(E52,2) -> 7.85 | C61: =C57 -> 2 | D61: =B61*C61 -> 15.7
A64: TOTAL INGRESOS BRUTOS | D64: =D11+D15+D19+D23+D27+D31+D35+E40+D44+F48+E57+D61 -> 845.52933
A66: BASE AFECTA (para aportes y descuentos)
A67: Incluye: Jornal semanal + DSO + BUC + Vacaciones + Asig. familiar + HE + Altitud + Altura
D68: =D11+D15+D19+D35+F48+E57+D27 -> 630.44
A69: No se considera: Indemnizaciones, Gratificaciones, Bonif. extraordinaria, Movilidad
A72: DESCUENTOS AL TRABAJADOR
A73: ONP | B73: 0.13 | C73: =$D$68*B73 -> 81.9572
A74: CONAFOVICER | B74: 0.02 | C74: =$D$68*B74 -> 12.6088
A75: Total descuentos | C75: =SUM(C73:C74) -> 94.566
A77: TOTAL SALARIO NETO A PAGAR | D77: =D64-C75 -> 750.96333
A80: APORTES DEL EMPLEADOR
A81: ESSALUD | B81: 0.09 | C81: =$D$68*B81 -> 56.7396
A82: SENCICO | B82: 0.002 | C82: =$D$68*B82 -> 1.26088
A83: Total aportes empleador | C83: =SUM(C81:C82) -> 58.00048
A86: COSTO TOTAL PARA LA EMPRESA | D86: =D64+C83 -> 903.52981
A89: Notas:
A90: • 2 HE totales: 2 al 60% (1 HE por día × 2 días, todas dentro de las primeras 2 diarias) + 0 al 100%.
A91: • Bonif. altitud: obra a 4,500 msnm (> 3,000 msnm) → S/ 2.50 × 6 días.
A92: • Sin hijos declarados → no aplica asignación escolar.
